tox_backtick/__about__.py
tox_backtick/__init__.py
tox_backtick/backquote.py
tox_backtick/py.typed
tox_backtick/setenv.py
tox_backtick-2.0.1.dist-info/licenses/LICENSE
tox_backtick-2.0.1.dist-info/METADATA
tox_backtick-2.0.1.dist-info/WHEEL
tox_backtick-2.0.1.dist-info/entry_points.txt
tox_backtick-2.0.1.dist-info/top_level.txt
tox_backtick-2.0.1.dist-info/zip-safe
tox_backtick-2.0.1.dist-info/RECORD
