Metadata-Version: 2.4
Name: tox-backtick
Version: 2.0.1
Summary: Backticks tox plugin for tox v.4.x.x.
Author: Steve Hespelt
Author-email: Adam Karpierz <adam@karpierz.net>, Damien Nadé <anvil.github+tox-backtocks@livna.org>
Maintainer-email: Adam Karpierz <adam@karpierz.net>
License-Expression: LGPL-2.1-or-later
Project-URL: Homepage, https://pypi.org/project/tox-backtick/
Project-URL: Documentation, https://karpierz.github.io/tox-backtick/
Project-URL: History, https://karpierz.github.io/tox-backtick/CHANGES.html
Project-URL: Download, https://pypi.org/project/tox-backtick/
Project-URL: Repository, https://github.com/karpierz/tox-backtick
Project-URL: Tracker, https://github.com/karpierz/tox-backtick/issues
Project-URL: Sponsoring, https://www.paypal.com/donate/?hosted_button_id=FX8L7CJUGLW7S
Keywords: tox,backtick,backtocks,backticks,backquotes
Platform: any
Classifier: Development Status :: 5 - Production/Stable
Classifier: Intended Audience :: Developers
Classifier: Operating System :: OS Independent
Classifier: Natural Language :: Polish
Classifier: Programming Language :: Python
Classifier: Programming Language :: Python :: 3
Classifier: Programming Language :: Python :: 3.10
Classifier: Programming Language :: Python :: 3.11
Classifier: Programming Language :: Python :: 3.12
Classifier: Programming Language :: Python :: 3.13
Classifier: Programming Language :: Python :: 3.14
Classifier: Programming Language :: Python :: 3 :: Only
Classifier: Programming Language :: Python :: Implementation :: CPython
Classifier: Programming Language :: Python :: Implementation :: PyPy
Classifier: Topic :: Software Development :: Quality Assurance
Classifier: Topic :: Software Development :: Testing
Classifier: Environment :: Console
Classifier: Framework :: tox
Classifier: Typing :: Typed
Requires-Python: <4.0.0,>=3.10.0
License-File: LICENSE
Requires-Dist: setuptools>=80.9.0
Requires-Dist: typing-extensions>=4.15.0
Requires-Dist: pkg-about>=2.0.0
Requires-Dist: tox>=4.34.1
Dynamic: license-file
